dulwich/__init__.py
dulwich/__main__.py
dulwich/_typing.py
dulwich/annotate.py
dulwich/approxidate.py
dulwich/archive.py
dulwich/attrs.py
dulwich/bisect.py
dulwich/bitmap.py
dulwich/bundle.py
dulwich/cli.py
dulwich/client.py
dulwich/commit_graph.py
dulwich/config.py
dulwich/credentials.py
dulwich/diff.py
dulwich/diff_tree.py
dulwich/diffstat.py
dulwich/dumb.py
dulwich/errors.py
dulwich/fastexport.py
dulwich/file.py
dulwich/filter_branch.py
dulwich/filters.py
dulwich/gc.py
dulwich/graph.py
dulwich/hooks.py
dulwich/ignore.py
dulwich/index.py
dulwich/lfs.py
dulwich/lfs_server.py
dulwich/line_ending.py
dulwich/log_utils.py
dulwich/lru_cache.py
dulwich/mailmap.py
dulwich/maintenance.py
dulwich/mbox.py
dulwich/merge.py
dulwich/merge_drivers.py
dulwich/midx.py
dulwich/notes.py
dulwich/object_format.py
dulwich/object_store.py
dulwich/objects.py
dulwich/objectspec.py
dulwich/pack.py
dulwich/patch.py
dulwich/protocol.py
dulwich/py.typed
dulwich/rebase.py
dulwich/reflog.py
dulwich/refs.py
dulwich/reftable.py
dulwich/repo.py
dulwich/rerere.py
dulwich/server.py
dulwich/sparse_patterns.py
dulwich/stash.py
dulwich/stripspace.py
dulwich/submodule.py
dulwich/trailers.py
dulwich/walk.py
dulwich/web.py
dulwich/whitespace.py
dulwich/worktree.py
dulwich/cloud/__init__.py
dulwich/cloud/gcs.py
dulwich/contrib/README.swift.rst
dulwich/contrib/__init__.py
dulwich/contrib/greenthreads.py
dulwich/contrib/paramiko_vendor.py
dulwich/contrib/release_robot.py
dulwich/contrib/requests_vendor.py
dulwich/contrib/swift.py
dulwich/porcelain/__init__.py
dulwich/porcelain/lfs.py
dulwich/porcelain/notes.py
dulwich/porcelain/submodule.py
dulwich/porcelain/tag.py
dulwich/porcelain/worktree.py
dulwich/tests/__init__.py
dulwich/tests/test_object_store.py
dulwich/tests/utils.py
dulwich-0.25.0.data/scripts/dul-receive-pack
dulwich-0.25.0.data/scripts/dul-upload-pack
dulwich-0.25.0.dist-info/licenses/COPYING
dulwich-0.25.0.dist-info/METADATA
dulwich-0.25.0.dist-info/WHEEL
dulwich-0.25.0.dist-info/entry_points.txt
dulwich-0.25.0.dist-info/top_level.txt
dulwich-0.25.0.dist-info/RECORD
