Metadata-Version: 2.4
Name: dulwich
Version: 0.25.0
Summary: Python Git Library
Author-email: Jelmer Vernooij <jelmer@jelmer.uk>
License-Expression: Apache-2.0 OR GPL-2.0-or-later
Project-URL: Homepage, https://www.dulwich.io/
Project-URL: Repository, https://www.dulwich.io/code/
Project-URL: GitHub, https://github.com/dulwich/dulwich
Project-URL: Bug Tracker, https://github.com/dulwich/dulwich/issues
Keywords: vcs,git
Classifier: Development Status :: 4 - Beta
Classifier: Programming Language :: Python :: 3.10
Classifier: Programming Language :: Python :: 3.11
Classifier: Programming Language :: Python :: 3.12
Classifier: Programming Language :: Python :: 3.13
Classifier: Programming Language :: Python :: 3.14
Classifier: Programming Language :: Python :: Implementation :: CPython
Classifier: Programming Language :: Python :: Implementation :: PyPy
Classifier: Operating System :: POSIX
Classifier: Operating System :: Microsoft :: Windows
Classifier: Topic :: Software Development :: Version Control
Requires-Python: >=3.10
License-File: COPYING
Requires-Dist: urllib3>=2.2.2
Requires-Dist: typing_extensions>=4.6.0; python_version < "3.12"
Provides-Extra: fastimport
Requires-Dist: fastimport; extra == "fastimport"
Provides-Extra: https
Requires-Dist: urllib3>=2.2.2; extra == "https"
Provides-Extra: pgp
Requires-Dist: gpg; extra == "pgp"
Provides-Extra: paramiko
Requires-Dist: paramiko; extra == "paramiko"
Provides-Extra: colordiff
Requires-Dist: rich; extra == "colordiff"
Provides-Extra: dev
Requires-Dist: ruff==0.14.7; extra == "dev"
Requires-Dist: mypy==1.19.0; extra == "dev"
Requires-Dist: dissolve>=0.1.1; extra == "dev"
Requires-Dist: codespell==2.4.1; extra == "dev"
Provides-Extra: merge
Requires-Dist: merge3; extra == "merge"
Provides-Extra: fuzzing
Requires-Dist: atheris; extra == "fuzzing"
Provides-Extra: patiencediff
Requires-Dist: patiencediff; extra == "patiencediff"
Dynamic: license-file
